MANIFEST.in
README.rst
pytestxu.py
setup.py
Pytestxj.egg-info/PKG-INFO
Pytestxj.egg-info/SOURCES.txt
Pytestxj.egg-info/dependency_links.txt
Pytestxj.egg-info/requires.txt
Pytestxj.egg-info/top_level.txt