Metadata-Version: 1.1
Name: Pytestxj
Version: 0.6.1
Summary: A test module for DataXujing
Home-page: https://dataxujing.github.io
Author: DataXujing
Author-email: xujing@inter-credit.net
License: Apache License, Version 2.0
Platform: linux/Windows
Classifier: Development Status :: 3 - Alpha
Classifier: Topic :: Text Processing
Classifier: License :: OSI Approved :: MIT License
Classifier: Programming Language :: Python :: 2
Classifier: Programming Language :: Python :: 2.7
Classifier: Programming Language :: Python :: 3
Classifier: Programming Language :: Python :: 3.5
